open_autonomy_client/__init__.py
open_autonomy_client/client.py
open_autonomy_client/downloader.py
open_autonomy_client-0.1.0.dist-info/LICENSE
open_autonomy_client-0.1.0.dist-info/METADATA
open_autonomy_client-0.1.0.dist-info/WHEEL
open_autonomy_client-0.1.0.dist-info/RECORD
